pix2vertex/__init__.py
pix2vertex/constants.py
pix2vertex/detector.py
pix2vertex/reconstructor.py
pix2vertex/utils.py
pix2vertex/models/__init__.py
pix2vertex/models/pix2pix.py
pix2vertex-1.0.4.dist-info/LICENSE
pix2vertex-1.0.4.dist-info/METADATA
pix2vertex-1.0.4.dist-info/WHEEL
pix2vertex-1.0.4.dist-info/top_level.txt
pix2vertex-1.0.4.dist-info/RECORD
