Metadata-Version: 2.1
Name: pix2vertex
Version: 1.0.4
Summary: 3D face reconstruction from a single image
Home-page: https://github.com/eladrich/pix2vertex.pytorch
Author: Elad Richardson, Matan Sela
Author-email: elad.richardson@gmail.com, matansel@gmail.com
License: UNKNOWN
Keywords: pix2vertex face reconstruction 3d pytorch pip package
Platform: UNKNOWN
Classifier: Environment :: Console
Classifier: Intended Audience :: Developers
Classifier: Intended Audience :: Science/Research
Classifier: Intended Audience :: Education
Classifier: Programming Language :: Python :: 3
Classifier: License :: OSI Approved :: MIT License
Classifier: Operating System :: OS Independent
Requires-Python: >=3.4
Requires-Dist: k3d (==2.7.4)
Requires-Dist: easydev (==0.9.38)
Requires-Dist: colormap (==1.0.3)
Requires-Dist: torch
Requires-Dist: imageio
Requires-Dist: dlib
Requires-Dist: scikit-image
Requires-Dist: matplotlib
Requires-Dist: tqdm
